{
    "magnification": "100x",
    "pixelDistance": 390,
    "realDistance": 100,
    "unit": "mm",
    "calibrationRatio": 0.2564102564102564,
    "timestamp": "2025-09-05T06:51:24.211Z",
    "imagePath": "C:\\Users\\Public\\MicroScope_Images\\microscope_100x_20250905_122053.jpg",
    "name": "100",
    "points": {
        "point1": {
            "x": 74,
            "y": 341.8000030517578
        },
        "point2": {
            "x": 464,
            "y": 341.8000030517578
        }
    },
    "coordinates": {
        "point1X": 74,
        "point1Y": 341.8000030517578,
        "point2X": 464,
        "point2Y": 341.8000030517578
    }
}